{
  "protocol_version" : "0.0.6",
  "configuration" : {
    "version" : "(6.13.0) (explicit/4c697eee)",
    "tlc" : "normal",
    "sigsgev" : "altstack",
    "notifications" : "kqueue",
    "architecture" : "amd64",
    "disabled_features" : "com,shared_perfcounters",
    "smallconfig" : "disabled",
    "bigarrays" : "disabled",
    "softdebug" : "enabled",
    "interpreter" : "enabled",
    "llvm_support" : "disabled",
    "suspend" : "preemptive"
  },
  "memory" : {
    "Resident Size" : "2402250752",
    "Virtual Size" : "40173944832",
    "minor_gc_time" : "0",
    "major_gc_time" : "2783265",
    "minor_gc_count" : "0",
    "major_gc_count" : "4",
    "major_gc_time_concurrent" : "0"
 },
  "threads" : [
 {
    "is_managed" : false,
    "offset_free_hash" : "0x0",
    "offset_rich_hash" : "0x0",
    "crashed" : false,
    "native_thread_id" : "0x3101c8000",
    "thread_info_addr" : "0x7f96d9fef600",
    "thread_name" : "tid_12403",
    "ctx" : {
      "IP" : "0x7ff815c339aa",
      "SP" : "0x3101c7d18",
      "BP" : "0x3101c7d30"
  },
    "unmanaged_frames" : [
  {
      "is_managed" : "false",
      "native_address" : "0x177367f96",
      "native_offset" : "0x00000"
   }
,
  {
      "is_managed" : "false",
      "native_address" : "0x1774c129c",
      "native_offset" : "0x00000"
   }
,
  {
      "is_managed" : "false",
      "native_address" : "0x1774c15d6",
      "native_offset" : "0x00000"
   }
,
  {
      "is_managed" : "false",
      "native_address" : "0x1774c138d",
      "native_offset" : "0x00000"
   }
,
  {
      "is_managed" : "false",
      "native_address" : "0x1773c5925",
      "native_offset" : "0x00000"
   }
,
  {
      "is_managed" : "false",
      "native_address" : "0x7ff815ca137d",
      "native_offset" : "0x00000"
   }
,
  {
      "is_managed" : "false",
      "native_address" : "0x7f96bba00000",
      "native_offset" : "0x00000"
   }
,
  {
      "is_managed" : "false",
      "native_address" : "0x7ff815acbf5f",
      "native_offset" : "0x00000"
   }
,
  {
      "is_managed" : "false",
      "native_address" : "0x1052811e8",
      "native_offset" : "0x00000"
   }
,
  {
      "is_managed" : "false",
      "native_address" : "0x102c2703a",
      "native_offset" : "0x00000"
   }
,
  {
      "is_managed" : "false",
      "native_address" : "0x102c285f5",
      "native_offset" : "0x00000"
   }
,
  {
      "is_managed" : "false",
      "native_address" : "0x102eb8d3b",
      "native_offset" : "0x00000"
   }
,
  {
      "is_managed" : "false",
      "native_address" : "0x7ff815c73202",
      "native_offset" : "0x00000"
   }
,
  {
      "is_managed" : "false",
      "native_address" : "0x7ff815c6ebab",
      "native_offset" : "0x00000"
   }

  ]
 },
 {
    "is_managed" : true,
    "offset_free_hash" : "0xbaa0c9715",
    "offset_rich_hash" : "0xbaa0c9afe",
    "crashed" : false,
    "native_thread_id" : "0x313ab9000",
    "thread_info_addr" : "0x7f96ae45f800",
    "thread_name" : "Burst-CompilerThread-2",
    "ctx" : {
      "IP" : "0x7ff815c365ce",
      "SP" : "0x313ab7bd8",
      "BP" : "0x313ab7c70"
  },
    "managed_frames" : [
  {
      "is_managed" : "false",
      "native_address" : "unregistered"
   }
,
  {
      "is_managed" : "true",
      "guid" : "EAA95166-E74C-4AE1-A419-B6AA5BAF90B9",
      "token" : "0x00000",
      "native_offset" : "0x0",
      "filename" : "mscorlib.dll",
      "sizeofimage" : "0x470000",
      "timestamp" : "0x8a9cbcb0",
      "il_offset" : "0x00000"
   }
,
  {
      "is_managed" : "true",
      "guid" : "EAA95166-E74C-4AE1-A419-B6AA5BAF90B9",
      "token" : "0x60020b3",
      "native_offset" : "0x0",
      "filename" : "mscorlib.dll",
      "sizeofimage" : "0x470000",
      "timestamp" : "0x8a9cbcb0",
      "il_offset" : "0x000c7"
   }
,
  {
      "is_managed" : "true",
      "guid" : "EAA95166-E74C-4AE1-A419-B6AA5BAF90B9",
      "token" : "0x60020a5",
      "native_offset" : "0x0",
      "filename" : "mscorlib.dll",
      "sizeofimage" : "0x470000",
      "timestamp" : "0x8a9cbcb0",
      "il_offset" : "0x000a1"
   }
,
  {
      "is_managed" : "true",
      "guid" : "EAA95166-E74C-4AE1-A419-B6AA5BAF90B9",
      "token" : "0x60020a9",
      "native_offset" : "0x0",
      "filename" : "mscorlib.dll",
      "sizeofimage" : "0x470000",
      "timestamp" : "0x8a9cbcb0",
      "il_offset" : "0x00000"
   }
,
  {
      "is_managed" : "true",
      "guid" : "9BE5D760-D820-4C7D-BC66-320FDD824250",
      "token" : "0x6003ffb",
      "native_offset" : "0x0",
      "filename" : "System.dll",
      "sizeofimage" : "0x29a000",
      "timestamp" : "0x9dd65995",
      "il_offset" : "0x0006e"
   }
,
  {
      "is_managed" : "true",
      "guid" : "9BE5D760-D820-4C7D-BC66-320FDD824250",
      "token" : "0x6003ffa",
      "native_offset" : "0x0",
      "filename" : "System.dll",
      "sizeofimage" : "0x29a000",
      "timestamp" : "0x9dd65995",
      "il_offset" : "0x0003c"
   }
,
  {
      "is_managed" : "true",
      "guid" : "9BE5D760-D820-4C7D-BC66-320FDD824250",
      "token" : "0x6003ff5",
      "native_offset" : "0x0",
      "filename" : "System.dll",
      "sizeofimage" : "0x29a000",
      "timestamp" : "0x9dd65995",
      "il_offset" : "0x00000"
   }
,
  {
      "is_managed" : "true",
      "guid" : "532A8A16-9E6A-4953-B5D9-A4C213B71772",
      "token" : "0x6000b49",
      "native_offset" : "0x0",
      "filename" : "Burst.Compiler.IL.dll",
      "sizeofimage" : "0x192000",
      "timestamp" : "0x9e316baa",
      "il_offset" : "0x00024"
   }
,
  {
      "is_managed" : "true",
      "guid" : "532A8A16-9E6A-4953-B5D9-A4C213B71772",
      "token" : "0x6000ba5",
      "native_offset" : "0x0",
      "filename" : "Burst.Compiler.IL.dll",
      "sizeofimage" : "0x192000",
      "timestamp" : "0x9e316baa",
      "il_offset" : "0x00096"
   }
,
  {
      "is_managed" : "true",
      "guid" : "EAA95166-E74C-4AE1-A419-B6AA5BAF90B9",
      "token" : "0x6001f7d",
      "native_offset" : "0x0",
      "filename" : "mscorlib.dll",
      "sizeofimage" : "0x470000",
      "timestamp" : "0x8a9cbcb0",
      "il_offset" : "0x00014"
   }
,
  {
      "is_managed" : "true",
      "guid" : "EAA95166-E74C-4AE1-A419-B6AA5BAF90B9",
      "token" : "0x6001f25",
      "native_offset" : "0x0",
      "filename" : "mscorlib.dll",
      "sizeofimage" : "0x470000",
      "timestamp" : "0x8a9cbcb0",
      "il_offset" : "0x00071"
   }
,
  {
      "is_managed" : "true",
      "guid" : "EAA95166-E74C-4AE1-A419-B6AA5BAF90B9",
      "token" : "0x6001f23",
      "native_offset" : "0x0",
      "filename" : "mscorlib.dll",
      "sizeofimage" : "0x470000",
      "timestamp" : "0x8a9cbcb0",
      "il_offset" : "0x00000"
   }
,
  {
      "is_managed" : "true",
      "guid" : "EAA95166-E74C-4AE1-A419-B6AA5BAF90B9",
      "token" : "0x6001f22",
      "native_offset" : "0x0",
      "filename" : "mscorlib.dll",
      "sizeofimage" : "0x470000",
      "timestamp" : "0x8a9cbcb0",
      "il_offset" : "0x0002b"
   }
,
  {
      "is_managed" : "true",
      "guid" : "EAA95166-E74C-4AE1-A419-B6AA5BAF90B9",
      "token" : "0x6001f7f",
      "native_offset" : "0x0",
      "filename" : "mscorlib.dll",
      "sizeofimage" : "0x470000",
      "timestamp" : "0x8a9cbcb0",
      "il_offset" : "0x00008"
   }
,
  {
      "is_managed" : "true",
      "guid" : "EAA95166-E74C-4AE1-A419-B6AA5BAF90B9",
      "token" : "0x00000",
      "native_offset" : "0x0",
      "filename" : "mscorlib.dll",
      "sizeofimage" : "0x470000",
      "timestamp" : "0x8a9cbcb0",
      "il_offset" : "0x00065"
   }

  ],
  "unmanaged_frames" : [
 {
    "is_managed" : "false",
    "native_address" : "0x177367f96",
    "native_offset" : "0x00000"
  }
,
 {
    "is_managed" : "false",
    "native_address" : "0x1774c129c",
    "native_offset" : "0x00000"
  }
,
 {
    "is_managed" : "false",
    "native_address" : "0x1774c15d6",
    "native_offset" : "0x00000"
  }
,
 {
    "is_managed" : "false",
    "native_address" : "0x1774c138d",
    "native_offset" : "0x00000"
  }
,
 {
    "is_managed" : "false",
    "native_address" : "0x1773c5925",
    "native_offset" : "0x00000"
  }
,
 {
    "is_managed" : "false",
    "native_address" : "0x7ff815ca137d",
    "native_offset" : "0x00000"
  }
,
 {
    "is_managed" : "false",
    "native_address" : "0x7ff815a94701",
    "native_offset" : "0x00000"
  }
,
 {
    "is_managed" : "false",
    "native_address" : "0x17750ff48",
    "native_offset" : "0x00000"
  }
,
 {
    "is_managed" : "false",
    "native_address" : "0x1774ccc3c",
    "native_offset" : "0x00000"
  }
,
 {
    "is_managed" : "false",
    "native_address" : "0x1774cc8e2",
    "native_offset" : "0x00000"
  }
,
 {
    "is_managed" : "false",
    "native_address" : "0x1774bca56",
    "native_offset" : "0x00000"
  }
,
 {
    "is_managed" : "false",
    "native_address" : "0x177467b62",
    "native_offset" : "0x00000"
  }
,
 {
    "is_managed" : "true",
    "guid" : "EAA95166-E74C-4AE1-A419-B6AA5BAF90B9",
    "token" : "0x00000",
    "native_offset" : "0x0",
    "filename" : "mscorlib.dll",
    "sizeofimage" : "0x470000",
    "timestamp" : "0x8a9cbcb0",
    "il_offset" : "0x00000"
  }
,
 {
    "is_managed" : "true",
    "guid" : "EAA95166-E74C-4AE1-A419-B6AA5BAF90B9",
    "token" : "0x60020a5",
    "native_offset" : "0x0",
    "filename" : "mscorlib.dll",
    "sizeofimage" : "0x470000",
    "timestamp" : "0x8a9cbcb0",
    "il_offset" : "0x00000"
  }

 ]
},
{
  "is_managed" : true,
  "offset_free_hash" : "0xbaa0c9715",
  "offset_rich_hash" : "0xbaa0c9afe",
  "crashed" : false,
  "native_thread_id" : "0x3140c2000",
  "thread_info_addr" : "0x7f96ae3d6800",
  "thread_name" : "Burst-CompilerThread-5",
  "ctx" : {
    "IP" : "0x7ff815c365ce",
    "SP" : "0x3140c0bd8",
    "BP" : "0x3140c0c70"
 },
  "managed_frames" : [
 {
    "is_managed" : "false",
    "native_address" : "unregistered"
  }
,
 {
    "is_managed" : "true",
    "guid" : "EAA95166-E74C-4AE1-A419-B6AA5BAF90B9",
    "token" : "0x00000",
    "native_offset" : "0x0",
    "filename" : "mscorlib.dll",
    "sizeofimage" : "0x470000",
    "timestamp" : "0x8a9cbcb0",
    "il_offset" : "0x00000"
  }
,
 {
    "is_managed" : "true",
    "guid" : "EAA95166-E74C-4AE1-A419-B6AA5BAF90B9",
    "token" : "0x60020b3",
    "native_offset" : "0x0",
    "filename" : "mscorlib.dll",
    "sizeofimage" : "0x470000",
    "timestamp" : "0x8a9cbcb0",
    "il_offset" : "0x000c7"
  }
,
 {
    "is_managed" : "true",
    "guid" : "EAA95166-E74C-4AE1-A419-B6AA5BAF90B9",
    "token" : "0x60020a5",
    "native_offset" : "0x0",
    "filename" : "mscorlib.dll",
    "sizeofimage" : "0x470000",
    "timestamp" : "0x8a9cbcb0",
    "il_offset" : "0x000a1"
  }
,
 {
    "is_managed" : "true",
    "guid" : "EAA95166-E74C-4AE1-A419-B6AA5BAF90B9",
    "token" : "0x60020a9",
    "native_offset" : "0x0",
    "filename" : "mscorlib.dll",
    "sizeofimage" : "0x470000",
    "timestamp" : "0x8a9cbcb0",
    "il_offset" : "0x00000"
  }
,
 {
    "is_managed" : "true",
    "guid" : "9BE5D760-D820-4C7D-BC66-320FDD824250",
    "token" : "0x6003ffb",
    "native_offset" : "0x0",
    "filename" : "System.dll",
    "sizeofimage" : "0x29a000",
    "timestamp" : "0x9dd65995",
    "il_offset" : "0x0006e"
  }
,
 {
    "is_managed" : "true",
    "guid" : "9BE5D760-D820-4C7D-BC66-320FDD824250",
    "token" : "0x6003ffa",
    "native_offset" : "0x0",
    "filename" : "System.dll",
    "sizeofimage" : "0x29a000",
    "timestamp" : "0x9dd65995",
    "il_offset" : "0x0003c"
  }
,
 {
    "is_managed" : "true",
    "guid" : "9BE5D760-D820-4C7D-BC66-320FDD824250",
    "token" : "0x6003ff5",
    "native_offset" : "0x0",
    "filename" : "System.dll",
    "sizeofimage" : "0x29a000",
    "timestamp" : "0x9dd65995",
    "il_offset" : "0x00000"
  }
,
 {
    "is_managed" : "true",
    "guid" : "532A8A16-9E6A-4953-B5D9-A4C213B71772",
    "token" : "0x6000b49",
    "native_offset" : "0x0",
    "filename" : "Burst.Compiler.IL.dll",
    "sizeofimage" : "0x192000",
    "timestamp" : "0x9e316baa",
    "il_offset" : "0x00024"
  }
,
 {
    "is_managed" : "true",
    "guid" : "532A8A16-9E6A-4953-B5D9-A4C213B71772",
    "token" : "0x6000ba5",
    "native_offset" : "0x0",
    "filename" : "Burst.Compiler.IL.dll",
    "sizeofimage" : "0x192000",
    "timestamp" : "0x9e316baa",
    "il_offset" : "0x00096"
  }
,
 {
    "is_managed" : "true",
    "guid" : "EAA95166-E74C-4AE1-A419-B6AA5BAF90B9",
    "token" : "0x6001f7d",
    "native_offset" : "0x0",
    "filename" : "mscorlib.dll",
    "sizeofimage" : "0x470000",
    "timestamp" : "0x8a9cbcb0",
    "il_offset" : "0x00014"
  }
,
 {
    "is_managed" : "true",
    "guid" : "EAA95166-E74C-4AE1-A419-B6AA5BAF90B9",
    "token" : "0x6001f25",
    "native_offset" : "0x0",
    "filename" : "mscorlib.dll",
    "sizeofimage" : "0x470000",
    "timestamp" : "0x8a9cbcb0",
    "il_offset" : "0x00071"
  }
,
 {
    "is_managed" : "true",
    "guid" : "EAA95166-E74C-4AE1-A419-B6AA5BAF90B9",
    "token" : "0x6001f23",
    "native_offset" : "0x0",
    "filename" : "mscorlib.dll",
    "sizeofimage" : "0x470000",
    "timestamp" : "0x8a9cbcb0",
    "il_offset" : "0x00000"
  }
,
 {
    "is_managed" : "true",
    "guid" : "EAA95166-E74C-4AE1-A419-B6AA5BAF90B9",
    "token" : "0x6001f22",
    "native_offset" : "0x0",
    "filename" : "mscorlib.dll",
    "sizeofimage" : "0x470000",
    "timestamp" : "0x8a9cbcb0",
    "il_offset" : "0x0002b"
  }
,
 {
    "is_managed" : "true",
    "guid" : "EAA95166-E74C-4AE1-A419-B6AA5BAF90B9",
    "token" : "0x6001f7f",
    "native_offset" : "0x0",
    "filename" : "mscorlib.dll",
    "sizeofimage" : "0x470000",
    "timestamp" : "0x8a9cbcb0",
    "il_offset" : "0x00008"
  }
,
 {
    "is_managed" : "true",
    "guid" : "EAA95166-E74C-4AE1-A419-B6AA5BAF90B9",
    "token" : "0x00000",
    "native_offset" : "0x0",
    "filename" : "mscorlib.dll",
    "sizeofimage" : "0x470000",
    "timestamp" : "0x8a9cbcb0",
    "il_offset" : "0x00065"
  }

 ],
"unmanaged_frames" : [
{
  "is_managed" : "false",
  "native_address" : "0x177367f96",
  "native_offset" : "0x00000"
 }
,
{
  "is_managed" : "false",
  "native_address" : "0x1774c129c",
  "native_offset" : "0x00000"
 }
,
{
  "is_managed" : "false",
  "native_address" : "0x1774c15d6",
  "native_offset" : "0x00000"
 }
,
{
  "is_managed" : "false",
  "native_address" : "0x1774c138d",
  "native_offset" : "0x00000"
 }
,
{
  "is_managed" : "false",
  "native_address" : "0x1773c5925",
  "native_offset" : "0x00000"
 }
,
{
  "is_managed" : "false",
  "native_address" : "0x7ff815ca137d",
  "native_offset" : "0x00000"
 }
,
{
  "is_managed" : "false",
  "native_address" : "0x1a5d3911c",
  "native_offset" : "0x00000"
 }
,
{
  "is_managed" : "false",
  "native_address" : "0x17750ff48",
  "native_offset" : "0x00000"
 }
,
{
  "is_managed" : "false",
  "native_address" : "0x1774ccc3c",
  "native_offset" : "0x00000"
 }
,
{
  "is_managed" : "false",
  "native_address" : "0x1774cc8e2",
  "native_offset" : "0x00000"
 }
,
{
  "is_managed" : "false",
  "native_address" : "0x1774bca56",
  "native_offset" : "0x00000"
 }
,
{
  "is_managed" : "false",
  "native_address" : "0x177467b62",
  "native_offset" : "0x00000"
 }
,
{
  "is_managed" : "true",
  "guid" : "EAA95166-E74C-4AE1-A419-B6AA5BAF90B9",
  "token" : "0x00000",
  "native_offset" : "0x0",
  "filename" : "mscorlib.dll",
  "sizeofimage" : "0x470000",
  "timestamp" : "0x8a9cbcb0",
  "il_offset" : "0x00000"
 }
,
{
  "is_managed" : "true",
  "guid" : "EAA95166-E74C-4AE1-A419-B6AA5BAF90B9",
  "token" : "0x60020a5",
  "native_offset" : "0x0",
  "filename" : "mscorlib.dll",
  "sizeofimage" : "0x470000",
  "timestamp" : "0x8a9cbcb0",
  "il_offset" : "0x00000"
 }

]
},
{
"is_managed" : false,
"offset_free_hash" : "0x0",
"offset_rich_hash" : "0x0",
"crashed" : false,
"native_thread_id" : "0x30fd2d000",
"thread_info_addr" : "0x7f96ab8fde00",
"thread_name" : "tid_10713",
"ctx" : {
  "IP" : "0x7ff815c339aa",
  "SP" : "0x30fd2cd18",
  "BP" : "0x30fd2cd30"
},
"unmanaged_frames" : [
{
  "is_managed" : "false",
  "native_address" : "0x177367f96",
  "native_offset" : "0x00000"
 }
,
{
  "is_managed" : "false",
  "native_address" : "0x1774c129c",
  "native_offset" : "0x00000"
 }
,
{
  "is_managed" : "false",
  "native_address" : "0x1774c15d6",
  "native_offset" : "0x00000"
 }
,
{
  "is_managed" : "false",
  "native_address" : "0x1774c138d",
  "native_offset" : "0x00000"
 }
,
{
  "is_managed" : "false",
  "native_address" : "0x1773c5925",
  "native_offset" : "0x00000"
 }
,
{
  "is_managed" : "false",
  "native_address" : "0x7ff815ca137d",
  "native_offset" : "0x00000"
 }
,
{
  "is_managed" : "false",
  "native_address" : "0xffffffff",
  "native_offset" : "0x00000"
 }
,
{
  "is_managed" : "false",
  "native_address" : "0x7ff815acbf5f",
  "native_offset" : "0x00000"
 }
,
{
  "is_managed" : "false",
  "native_address" : "0x1052811e8",
  "native_offset" : "0x00000"
 }
,
{
  "is_managed" : "false",
  "native_address" : "0x102c2703a",
  "native_offset" : "0x00000"
 }
,
{
  "is_managed" : "false",
  "native_address" : "0x102c285f5",
  "native_offset" : "0x00000"
 }
,
{
  "is_managed" : "false",
  "native_address" : "0x102eb8d3b",
  "native_offset" : "0x00000"
 }
,
{
  "is_managed" : "false",
  "native_address" : "0x7ff815c73202",
  "native_offset" : "0x00000"
 }
,
{
  "is_managed" : "false",
  "native_address" : "0x7ff815c6ebab",
  "native_offset" : "0x00000"
 }

]
},
{
"is_managed" : true,
"offset_free_hash" : "0xeec5a6c14",
"offset_rich_hash" : "0xeec5a6f9a",
"crashed" : false,
"native_thread_id" : "0x3146cb000",
"thread_info_addr" : "0x7f96af124800",
"thread_name" : "Burst-ProgressReporter",
"ctx" : {
  "IP" : "0x7ff815c365ce",
  "SP" : "0x3146ca218",
  "BP" : "0x3146ca2b0"
},
"managed_frames" : [
{
  "is_managed" : "false",
  "native_address" : "unregistered"
 }
,
{
  "is_managed" : "true",
  "guid" : "EAA95166-E74C-4AE1-A419-B6AA5BAF90B9",
  "token" : "0x00000",
  "native_offset" : "0x0",
  "filename" : "mscorlib.dll",
  "sizeofimage" : "0x470000",
  "timestamp" : "0x8a9cbcb0",
  "il_offset" : "0x00000"
 }
,
{
  "is_managed" : "true",
  "guid" : "EAA95166-E74C-4AE1-A419-B6AA5BAF90B9",
  "token" : "0x6001f5d",
  "native_offset" : "0x0",
  "filename" : "mscorlib.dll",
  "sizeofimage" : "0x470000",
  "timestamp" : "0x8a9cbcb0",
  "il_offset" : "0x0002f"
 }
,
{
  "is_managed" : "true",
  "guid" : "EAA95166-E74C-4AE1-A419-B6AA5BAF90B9",
  "token" : "0x6001f50",
  "native_offset" : "0x0",
  "filename" : "mscorlib.dll",
  "sizeofimage" : "0x470000",
  "timestamp" : "0x8a9cbcb0",
  "il_offset" : "0x0000e"
 }
,
{
  "is_managed" : "true",
  "guid" : "EAA95166-E74C-4AE1-A419-B6AA5BAF90B9",
  "token" : "0x6001f52",
  "native_offset" : "0x0",
  "filename" : "mscorlib.dll",
  "sizeofimage" : "0x470000",
  "timestamp" : "0x8a9cbcb0",
  "il_offset" : "0x00000"
 }
,
{
  "is_managed" : "true",
  "guid" : "EAA95166-E74C-4AE1-A419-B6AA5BAF90B9",
  "token" : "0x6001ea2",
  "native_offset" : "0x0",
  "filename" : "mscorlib.dll",
  "sizeofimage" : "0x470000",
  "timestamp" : "0x8a9cbcb0",
  "il_offset" : "0x0001d"
 }
,
{
  "is_managed" : "true",
  "guid" : "EAA95166-E74C-4AE1-A419-B6AA5BAF90B9",
  "token" : "0x6001ea1",
  "native_offset" : "0x0",
  "filename" : "mscorlib.dll",
  "sizeofimage" : "0x470000",
  "timestamp" : "0x8a9cbcb0",
  "il_offset" : "0x000d9"
 }
,
{
  "is_managed" : "true",
  "guid" : "9BE5D760-D820-4C7D-BC66-320FDD824250",
  "token" : "0x6003fe9",
  "native_offset" : "0x0",
  "filename" : "System.dll",
  "sizeofimage" : "0x29a000",
  "timestamp" : "0x9dd65995",
  "il_offset" : "0x00067"
 }
,
{
  "is_managed" : "true",
  "guid" : "9BE5D760-D820-4C7D-BC66-320FDD824250",
  "token" : "0x6003fe8",
  "native_offset" : "0x0",
  "filename" : "System.dll",
  "sizeofimage" : "0x29a000",
  "timestamp" : "0x9dd65995",
  "il_offset" : "0x00006"
 }
,
{
  "is_managed" : "true",
  "guid" : "9BE5D760-D820-4C7D-BC66-320FDD824250",
  "token" : "0x6003fe4",
  "native_offset" : "0x0",
  "filename" : "System.dll",
  "sizeofimage" : "0x29a000",
  "timestamp" : "0x9dd65995",
  "il_offset" : "0x00000"
 }
,
{
  "is_managed" : "true",
  "guid" : "532A8A16-9E6A-4953-B5D9-A4C213B71772",
  "token" : "0x6001057",
  "native_offset" : "0x0",
  "filename" : "Burst.Compiler.IL.dll",
  "sizeofimage" : "0x192000",
  "timestamp" : "0x9e316baa",
  "il_offset" : "0x000c9"
 }
,
{
  "is_managed" : "true",
  "guid" : "EAA95166-E74C-4AE1-A419-B6AA5BAF90B9",
  "token" : "0x6001f7d",
  "native_offset" : "0x0",
  "filename" : "mscorlib.dll",
  "sizeofimage" : "0x470000",
  "timestamp" : "0x8a9cbcb0",
  "il_offset" : "0x00014"
 }
,
{
  "is_managed" : "true",
  "guid" : "EAA95166-E74C-4AE1-A419-B6AA5BAF90B9",
  "token" : "0x6001f25",
  "native_offset" : "0x0",
  "filename" : "mscorlib.dll",
  "sizeofimage" : "0x470000",
  "timestamp" : "0x8a9cbcb0",
  "il_offset" : "0x00071"
 }
,
{
  "is_managed" : "true",
  "guid" : "EAA95166-E74C-4AE1-A419-B6AA5BAF90B9",
  "token" : "0x6001f23",
  "native_offset" : "0x0",
  "filename" : "mscorlib.dll",
  "sizeofimage" : "0x470000",
  "timestamp" : "0x8a9cbcb0",
  "il_offset" : "0x00000"
 }
,
{
  "is_managed" : "true",
  "guid" : "EAA95166-E74C-4AE1-A419-B6AA5BAF90B9",
  "token" : "0x6001f22",
  "native_offset" : "0x0",
  "filename" : "mscorlib.dll",
  "sizeofimage" : "0x470000",
  "timestamp" : "0x8a9cbcb0",
  "il_offset" : "0x0002b"
 }
,
{
  "is_managed" : "true",
  "guid" : "EAA95166-E74C-4AE1-A419-B6AA5BAF90B9",
  "token" : "0x6001f7f",
  "native_offset" : "0x0",
  "filename" : "mscorlib.dll",
  "sizeofimage" : "0x470000",
  "timestamp" : "0x8a9cbcb0",
  "il_offset" : "0x00008"
 }
,
{
  "is_managed" : "true",
  "guid" : "EAA95166-E74C-4AE1-A419-B6AA5BAF90B9",
  "token" : "0x00000",
  "native_offset" : "0x0",
  "filename" : "mscorlib.dll",
  "sizeofimage" : "0x470000",
  "timestamp" : "0x8a9cbcb0",
  "il_offset" : "0x00065"
 }

],
"unmanaged_frames" : [
{
"is_managed" : "false",
"native_address" : "0x177367f96",
"native_offset" : "0x00000"
}
,
{
"is_managed" : "false",
"native_address" : "0x1774c129c",
"native_offset" : "0x00000"
}
,
{
"is_managed" : "false",
"native_address" : "0x1774c15d6",
"native_offset" : "0x00000"
}
,
{
"is_managed" : "false",
"native_address" : "0x1774c138d",
"native_offset" : "0x00000"
}
,
{
"is_managed" : "false",
"native_address" : "0x1773c5925",
"native_offset" : "0x00000"
}
,
{
"is_managed" : "false",
"native_address" : "0x7ff815ca137d",
"native_offset" : "0x00000"
}
,
{
"is_managed" : "false",
"native_address" : "0x177523a89",
"native_offset" : "0x00000"
}
,
{
"is_managed" : "false",
"native_address" : "0x17750ff48",
"native_offset" : "0x00000"
}
,
{
"is_managed" : "false",
"native_address" : "0x1774cc301",
"native_offset" : "0x00000"
}
,
{
"is_managed" : "false",
"native_address" : "0x1774cc163",
"native_offset" : "0x00000"
}
,
{
"is_managed" : "false",
"native_address" : "0x1774fcb0b",
"native_offset" : "0x00000"
}
,
{
"is_managed" : "false",
"native_address" : "0x17746642b",
"native_offset" : "0x00000"
}
,
{
"is_managed" : "true",
"guid" : "EAA95166-E74C-4AE1-A419-B6AA5BAF90B9",
"token" : "0x00000",
"native_offset" : "0x0",
"filename" : "mscorlib.dll",
"sizeofimage" : "0x470000",
"timestamp" : "0x8a9cbcb0",
"il_offset" : "0x00000"
}
,
{
"is_managed" : "true",
"guid" : "EAA95166-E74C-4AE1-A419-B6AA5BAF90B9",
"token" : "0x6001f50",
"native_offset" : "0x0",
"filename" : "mscorlib.dll",
"sizeofimage" : "0x470000",
"timestamp" : "0x8a9cbcb0",
"il_offset" : "0x00000"
}
,
{
"is_managed" : "true",
"guid" : "9BE5D760-D820-4C7D-BC66-320FDD824250",
"token" : "0x6003fe9",
"native_offset" : "0x0",
"filename" : "System.dll",
"sizeofimage" : "0x29a000",
"timestamp" : "0x9dd65995",
"il_offset" : "0x00000"
}
,
{
"is_managed" : "true",
"guid" : "9BE5D760-D820-4C7D-BC66-320FDD824250",
"token" : "0x6003fe8",
"native_offset" : "0x0",
"filename" : "System.dll",
"sizeofimage" : "0x29a000",
"timestamp" : "0x9dd65995",
"il_offset" : "0x00000"
}
,
{
"is_managed" : "true",
"guid" : "EAA95166-E74C-4AE1-A419-B6AA5BAF90B9",
"token" : "0x6001f7d",
"native_offset" : "0x0",
"filename" : "mscorlib.dll",
"sizeofimage" : "0x470000",
"timestamp" : "0x8a9cbcb0",
"il_offset" : "0x00000"
}
,
{
"is_managed" : "true",
"guid" : "EAA95166-E74C-4AE1-A419-B6AA5BAF90B9",
"token" : "0x6001f23",
"native_offset" : "0x0",
"filename" : "mscorlib.dll",
"sizeofimage" : "0x470000",
"timestamp" : "0x8a9cbcb0",
"il_offset" : "0x00000"
}
,
{
"is_managed" : "false",
"native_address" : "0x1772eb7fc",
"native_offset" : "0x00000"
}
,
{
"is_managed" : "false",
"native_address" : "0x1774a1183",
"native_offset" : "0x00000"
}
,
{
"is_managed" : "false",
"native_address" : "0x1774a2cb5",
"native_offset" : "0x00000"
}
,
{
"is_managed" : "false",
"native_address" : "0x1774c20b8",
"native_offset" : "0x00000"
}
,
{
"is_managed" : "false",
"native_address" : "0x1774c1e89",
"native_offset" : "0x00000"
}
,
{
"is_managed" : "false",
"native_address" : "0x17753f3a5",
"native_offset" : "0x00000"
}
,
{
"is_managed" : "false",
"native_address" : "0x17753f33d",
"native_offset" : "0x00000"
}
,
{
"is_managed" : "false",
"native_address" : "0x7ff815c73202",
"native_offset" : "0x00000"
}
,
{
"is_managed" : "false",
"native_address" : "0x7ff815c6ebab",
"native_offset" : "0x00000"
}

]
},
{
"is_managed" : false,
"offset_free_hash" : "0x0",
"offset_rich_hash" : "0x0",
"crashed" : false,
"native_thread_id" : "0x311e8f000",
"thread_info_addr" : "0x7f96ab6a4a00",
"thread_name" : "Thread Pool Worker",
"ctx" : {
"IP" : "0x7ff815c339c2",
"SP" : "0x311e8edf8",
"BP" : "0x311e8ee60"
},
"unmanaged_frames" : [
{
"is_managed" : "false",
"native_address" : "0x177367f96",
"native_offset" : "0x00000"
}
,
{
"is_managed" : "false",
"native_address" : "0x1774c129c",
"native_offset" : "0x00000"
}
,
{
"is_managed" : "false",
"native_address" : "0x1774c15d6",
"native_offset" : "0x00000"
}
,
{
"is_managed" : "false",
"native_address" : "0x1774c138d",
"native_offset" : "0x00000"
}
,
{
"is_managed" : "false",
"native_address" : "0x1773c5925",
"native_offset" : "0x00000"
}
,
{
"is_managed" : "false",
"native_address" : "0x7ff815ca137d",
"native_offset" : "0x00000"
}
,
{
"is_managed" : "false",
"native_address" : "0x117de0a00",
"native_offset" : "0x00000"
}
,
{
"is_managed" : "false",
"native_address" : "0x1774c1fe4",
"native_offset" : "0x00000"
}
,
{
"is_managed" : "false",
"native_address" : "0x1774c1e89",
"native_offset" : "0x00000"
}
,
{
"is_managed" : "false",
"native_address" : "0x17753f3a5",
"native_offset" : "0x00000"
}
,
{
"is_managed" : "false",
"native_address" : "0x17753f33d",
"native_offset" : "0x00000"
}
,
{
"is_managed" : "false",
"native_address" : "0x7ff815c73202",
"native_offset" : "0x00000"
}
,
{
"is_managed" : "false",
"native_address" : "0x7ff815c6ebab",
"native_offset" : "0x00000"
}

]
},
{
"is_managed" : false,
"offset_free_hash" : "0x0",
"offset_rich_hash" : "0x0",
"crashed" : false,
"native_thread_id" : "0x312498000",
"thread_info_addr" : "0x7f96ab73ae00",
"thread_name" : "Thread Pool Worker",
"ctx" : {
"IP" : "0x7ff815c339c2",
"SP" : "0x312497df8",
"BP" : "0x312497e60"
},
"unmanaged_frames" : [
{
"is_managed" : "false",
"native_address" : "0x177367f96",
"native_offset" : "0x00000"
}
,
{
"is_managed" : "false",
"native_address" : "0x1774c129c",
"native_offset" : "0x00000"
}
,
{
"is_managed" : "false",
"native_address" : "0x1774c15d6",
"native_offset" : "0x00000"
}
,
{
"is_managed" : "false",
"native_address" : "0x1774c138d",
"native_offset" : "0x00000"
}
,
{
"is_managed" : "false",
"native_address" : "0x1773c5925",
"native_offset" : "0x00000"
}
,
{
"is_managed" : "false",
"native_address" : "0x7ff815ca137d",
"native_offset" : "0x00000"
}
,
{
"is_managed" : "false",
"native_address" : "0x526",
"native_offset" : "0x00000"
}
,
{
"is_managed" : "false",
"native_address" : "0x1774c1fe4",
"native_offset" : "0x00000"
}
,
{
"is_managed" : "false",
"native_address" : "0x1774c1e89",
"native_offset" : "0x00000"
}
,
{
"is_managed" : "false",
"native_address" : "0x17753f3a5",
"native_offset" : "0x00000"
}
,
{
"is_managed" : "false",
"native_address" : "0x17753f33d",
"native_offset" : "0x00000"
}
,
{
"is_managed" : "false",
"native_address" : "0x7ff815c73202",
"native_offset" : "0x00000"
}
,
{
"is_managed" : "false",
"native_address" : "0x7ff815c6ebab",
"native_offset" : "0x00000"
}

]
},
{
"is_managed" : false,
"offset_free_hash" : "0x0",
"offset_rich_hash" : "0x0",
"crashed" : false,
"native_thread_id" : "0x30fb9a000",
"thread_info_addr" : "0x7f96da324e00",
"thread_name" : "tid_598f",
"ctx" : {
"IP" : "0x7ff815c339aa",
"SP" : "0x30fb99dc8",
"BP" : "0x30fb99de0"
},
"unmanaged_frames" : [
{
"is_managed" : "false",
"native_address" : "0x177367f96",
"native_offset" : "0x00000"
}
,
{
"is_managed" : "false",
"native_address" : "0x1774c129c",
"native_offset" : "0x00000"
}
,
{
"is_managed" : "false",
"native_address" : "0x1774c15d6",
"native_offset" : "0x00000"
}
,
{
"is_managed" : "false",
"native_address" : "0x1774c138d",
"native_offset" : "0x00000"
}
,
{
"is_managed" : "false",
"native_address" : "0x1773c5925",
"native_offset" : "0x00000"
}
,
{
"is_managed" : "false",
"native_address" : "0x7ff815ca137d",
"native_offset" : "0x00000"
}
,
{
"is_managed" : "false",
"native_address" : "0x104e4573f",
"native_offset" : "0x00000"
}
,
{
"is_managed" : "false",
"native_address" : "0x7ff815acbf5f",
"native_offset" : "0x00000"
}
,
{
"is_managed" : "false",
"native_address" : "0x1052811e8",
"native_offset" : "0x00000"
}
,
{
"is_managed" : "false",
"native_address" : "0x10288d2ba",
"native_offset" : "0x00000"
}
,
{
"is_managed" : "false",
"native_address" : "0x102ceb2bd",
"native_offset" : "0x00000"
}
,
{
"is_managed" : "false",
"native_address" : "0x102ceb248",
"native_offset" : "0x00000"
}
,
{
"is_managed" : "false",
"native_address" : "0x102eb8d3b",
"native_offset" : "0x00000"
}
,
{
"is_managed" : "false",
"native_address" : "0x7ff815c73202",
"native_offset" : "0x00000"
}
,
{
"is_managed" : "false",
"native_address" : "0x7ff815c6ebab",
"native_offset" : "0x00000"
}

]
},
{
"is_managed" : false,
"offset_free_hash" : "0x0",
"offset_rich_hash" : "0x0",
"crashed" : false,
"native_thread_id" : "0x3130aa000",
"thread_info_addr" : "0x7f96ac812200",
"thread_name" : "Thread Pool Worker",
"ctx" : {
"IP" : "0x7ff815c339c2",
"SP" : "0x3130a9df8",
"BP" : "0x3130a9e60"
},
"unmanaged_frames" : [
{
"is_managed" : "false",
"native_address" : "0x177367f96",
"native_offset" : "0x00000"
}
,
{
"is_managed" : "false",
"native_address" : "0x1774c129c",
"native_offset" : "0x00000"
}
,
{
"is_managed" : "false",
"native_address" : "0x1774c15d6",
"native_offset" : "0x00000"
}
,
{
"is_managed" : "false",
"native_address" : "0x1774c138d",
"native_offset" : "0x00000"
}
,
{
"is_managed" : "false",
"native_address" : "0x1773c5925",
"native_offset" : "0x00000"
}
,
{
"is_managed" : "false",
"native_address" : "0x7ff815ca137d",
"native_offset" : "0x00000"
}
,
{
"is_managed" : "false",
"native_address" : "0x3130a8e10",
"native_offset" : "0x00000"
}
,
{
"is_managed" : "false",
"native_address" : "0x1774c1fe4",
"native_offset" : "0x00000"
}
,
{
"is_managed" : "false",
"native_address" : "0x1774c1e89",
"native_offset" : "0x00000"
}
,
{
"is_managed" : "false",
"native_address" : "0x17753f3a5",
"native_offset" : "0x00000"
}
,
{
"is_managed" : "false",
"native_address" : "0x17753f33d",
"native_offset" : "0x00000"
}
,
{
"is_managed" : "false",
"native_address" : "0x7ff815c73202",
"native_offset" : "0x00000"
}
,
{
"is_managed" : "false",
"native_address" : "0x7ff815c6ebab",
"native_offset" : "0x00000"
}

]
},
{
"is_managed" : true,
"offset_free_hash" : "0x120f84f71",
"offset_rich_hash" : "0x120f84fa6",
"crashed" : true,
"native_thread_id" : "0x208ea6240",
"thread_info_addr" : "0x7f96d89a7000",
"thread_name" : "tid_103",
"ctx" : {
"IP" : "0x1ec132ca4",
"SP" : "0x30f23c110",
"BP" : "0x30f23c110"
},
"managed_frames" : [
{
"is_managed" : "false",
"native_address" : "unregistered"
}
,
{
"is_managed" : "true",
"guid" : "B2E18436-7179-4692-8475-DBFDBD76EE08",
"token" : "0x600101f",
"native_offset" : "0x0",
"filename" : "Oculus.Interaction.dll",
"sizeofimage" : "0xd0000",
"timestamp" : "0xd3cf15b4",
"il_offset" : "0x0000b"
}
,
{
"is_managed" : "true",
"guid" : "EAA95166-E74C-4AE1-A419-B6AA5BAF90B9",
"token" : "0x00000",
"native_offset" : "0x0",
"filename" : "mscorlib.dll",
"sizeofimage" : "0x470000",
"timestamp" : "0x8a9cbcb0",
"il_offset" : "0x0002a"
}

]
},
{
"is_managed" : false,
"offset_free_hash" : "0x0",
"offset_rich_hash" : "0x0",
"crashed" : false,
"native_thread_id" : "0x311780000",
"thread_info_addr" : "0x7f96d996aa00",
"thread_name" : "Finalizer",
"ctx" : {
"IP" : "0x7ff815c339aa",
"SP" : "0x31177fe18",
"BP" : "0x31177fe60"
},
"unmanaged_frames" : [
{
"is_managed" : "false",
"native_address" : "0x177367f96",
"native_offset" : "0x00000"
}
,
{
"is_managed" : "false",
"native_address" : "0x1774c129c",
"native_offset" : "0x00000"
}
,
{
"is_managed" : "false",
"native_address" : "0x1774c15d6",
"native_offset" : "0x00000"
}
,
{
"is_managed" : "false",
"native_address" : "0x1774c138d",
"native_offset" : "0x00000"
}
,
{
"is_managed" : "false",
"native_address" : "0x1773c5925",
"native_offset" : "0x00000"
}
,
{
"is_managed" : "false",
"native_address" : "0x7ff815ca137d",
"native_offset" : "0x00000"
}
,
{
"is_managed" : "false",
"native_address" : "unregistered"
}
,
{
"is_managed" : "false",
"native_address" : "0x1774c1fe4",
"native_offset" : "0x00000"
}
,
{
"is_managed" : "false",
"native_address" : "0x1774c1e89",
"native_offset" : "0x00000"
}
,
{
"is_managed" : "false",
"native_address" : "0x17753f3a5",
"native_offset" : "0x00000"
}
,
{
"is_managed" : "false",
"native_address" : "0x17753f33d",
"native_offset" : "0x00000"
}
,
{
"is_managed" : "false",
"native_address" : "0x7ff815c73202",
"native_offset" : "0x00000"
}
,
{
"is_managed" : "false",
"native_address" : "0x7ff815c6ebab",
"native_offset" : "0x00000"
}

]
},
{
"is_managed" : true,
"offset_free_hash" : "0xbaa0c9715",
"offset_rich_hash" : "0xbaa0c9afe",
"crashed" : false,
"native_thread_id" : "0x313cbc000",
"thread_info_addr" : "0x7f96af105c00",
"thread_name" : "Burst-CompilerThread-3",
"ctx" : {
"IP" : "0x7ff815c365ce",
"SP" : "0x313cbabd8",
"BP" : "0x313cbac70"
},
"managed_frames" : [
{
"is_managed" : "false",
"native_address" : "unregistered"
}
,
{
"is_managed" : "true",
"guid" : "EAA95166-E74C-4AE1-A419-B6AA5BAF90B9",
"token" : "0x00000",
"native_offset" : "0x0",
"filename" : "mscorlib.dll",
"sizeofimage" : "0x470000",
"timestamp" : "0x8a9cbcb0",
"il_offset" : "0x00000"
}
,
{
"is_managed" : "true",
"guid" : "EAA95166-E74C-4AE1-A419-B6AA5BAF90B9",
"token" : "0x60020b3",
"native_offset" : "0x0",
"filename" : "mscorlib.dll",
"sizeofimage" : "0x470000",
"timestamp" : "0x8a9cbcb0",
"il_offset" : "0x000c7"
}
,
{
"is_managed" : "true",
"guid" : "EAA95166-E74C-4AE1-A419-B6AA5BAF90B9",
"token" : "0x60020a5",
"native_offset" : "0x0",
"filename" : "mscorlib.dll",
"sizeofimage" : "0x470000",
"timestamp" : "0x8a9cbcb0",
"il_offset" : "0x000a1"
}
,
{
"is_managed" : "true",
"guid" : "EAA95166-E74C-4AE1-A419-B6AA5BAF90B9",
"token" : "0x60020a9",
"native_offset" : "0x0",
"filename" : "mscorlib.dll",
"sizeofimage" : "0x470000",
"timestamp" : "0x8a9cbcb0",
"il_offset" : "0x00000"
}
,
{
"is_managed" : "true",
"guid" : "9BE5D760-D820-4C7D-BC66-320FDD824250",
"token" : "0x6003ffb",
"native_offset" : "0x0",
"filename" : "System.dll",
"sizeofimage" : "0x29a000",
"timestamp" : "0x9dd65995",
"il_offset" : "0x0006e"
}
,
{
"is_managed" : "true",
"guid" : "9BE5D760-D820-4C7D-BC66-320FDD824250",
"token" : "0x6003ffa",
"native_offset" : "0x0",
"filename" : "System.dll",
"sizeofimage" : "0x29a000",
"timestamp" : "0x9dd65995",
"il_offset" : "0x0003c"
}
,
{
"is_managed" : "true",
"guid" : "9BE5D760-D820-4C7D-BC66-320FDD824250",
"token" : "0x6003ff5",
"native_offset" : "0x0",
"filename" : "System.dll",
"sizeofimage" : "0x29a000",
"timestamp" : "0x9dd65995",
"il_offset" : "0x00000"
}
,
{
"is_managed" : "true",
"guid" : "532A8A16-9E6A-4953-B5D9-A4C213B71772",
"token" : "0x6000b49",
"native_offset" : "0x0",
"filename" : "Burst.Compiler.IL.dll",
"sizeofimage" : "0x192000",
"timestamp" : "0x9e316baa",
"il_offset" : "0x00024"
}
,
{
"is_managed" : "true",
"guid" : "532A8A16-9E6A-4953-B5D9-A4C213B71772",
"token" : "0x6000ba5",
"native_offset" : "0x0",
"filename" : "Burst.Compiler.IL.dll",
"sizeofimage" : "0x192000",
"timestamp" : "0x9e316baa",
"il_offset" : "0x00096"
}
,
{
"is_managed" : "true",
"guid" : "EAA95166-E74C-4AE1-A419-B6AA5BAF90B9",
"token" : "0x6001f7d",
"native_offset" : "0x0",
"filename" : "mscorlib.dll",
"sizeofimage" : "0x470000",
"timestamp" : "0x8a9cbcb0",
"il_offset" : "0x00014"
}
,
{
"is_managed" : "true",
"guid" : "EAA95166-E74C-4AE1-A419-B6AA5BAF90B9",
"token" : "0x6001f25",
"native_offset" : "0x0",
"filename" : "mscorlib.dll",
"sizeofimage" : "0x470000",
"timestamp" : "0x8a9cbcb0",
"il_offset" : "0x00071"
}
,
{
"is_managed" : "true",
"guid" : "EAA95166-E74C-4AE1-A419-B6AA5BAF90B9",
"token" : "0x6001f23",
"native_offset" : "0x0",
"filename" : "mscorlib.dll",
"sizeofimage" : "0x470000",
"timestamp" : "0x8a9cbcb0",
"il_offset" : "0x00000"
}
,
{
"is_managed" : "true",
"guid" : "EAA95166-E74C-4AE1-A419-B6AA5BAF90B9",
"token" : "0x6001f22",
"native_offset" : "0x0",
"filename" : "mscorlib.dll",
"sizeofimage" : "0x470000",
"timestamp" : "0x8a9cbcb0",
"il_offset" : "0x0002b"
}
,
{
"is_managed" : "true",
"guid" : "EAA95166-E74C-4AE1-A419-B6AA5BAF90B9",
"token" : "0x6001f7f",
"native_offset" : "0x0",
"filename" : "mscorlib.dll",
"sizeofimage" : "0x470000",
"timestamp" : "0x8a9cbcb0",
"il_offset" : "0x00008"
}
,
{
"is_managed" : "true",
"guid" : "EAA95166-E74C-4AE1-A419-B6AA5BAF90B9",
"token" : "0x00000",
"native_offset" : "0x0",
"filename" : "mscorlib.dll",
"sizeofimage" : "0x470000",
"timestamp" : "0x8a9cbcb0",
"il_offset" : "0x00065"
}

],
"unmanaged_frames" : [
{
"is_managed" : "false",
"native_address" : "0x177367f96",
"native_offset" : "0x00000"
}
,
{
"is_managed" : "false",
"native_address" : "0x1774c129c",
"native_offset" : "0x00000"
}
,
{
"is_managed" : "false",
"native_address" : "0x1774c15d6",
"native_offset" : "0x00000"
}
,
{
"is_managed" : "false",
"native_address" : "0x1774c138d",
"native_offset" : "0x00000"
}
,
{
"is_managed" : "false",
"native_address" : "0x1773c5925",
"native_offset" : "0x00000"
}
,
{
"is_managed" : "false",
"native_address" : "0x7ff815ca137d",
"native_offset" : "0x00000"
}
,
{
"is_managed" : "false",
"native_address" : "0x7ff815a94701",
"native_offset" : "0x00000"
}
,
{
"is_managed" : "false",
"native_address" : "0x17750ff48",
"native_offset" : "0x00000"
}
,
{
"is_managed" : "false",
"native_address" : "0x1774ccc3c",
"native_offset" : "0x00000"
}
,
{
"is_managed" : "false",
"native_address" : "0x1774cc8e2",
"native_offset" : "0x00000"
}
,
{
"is_managed" : "false",
"native_address" : "0x1774bca56",
"native_offset" : "0x00000"
}
,
{
"is_managed" : "false",
"native_address" : "0x177467b62",
"native_offset" : "0x00000"
}
,
{
"is_managed" : "true",
"guid" : "EAA95166-E74C-4AE1-A419-B6AA5BAF90B9",
"token" : "0x00000",
"native_offset" : "0x0",
"filename" : "mscorlib.dll",
"sizeofimage" : "0x470000",
"timestamp" : "0x8a9cbcb0",
"il_offset" : "0x00000"
}
,
{
"is_managed" : "true",
"guid" : "EAA95166-E74C-4AE1-A419-B6AA5BAF90B9",
"token" : "0x60020a5",
"native_offset" : "0x0",
"filename" : "mscorlib.dll",
"sizeofimage" : "0x470000",
"timestamp" : "0x8a9cbcb0",
"il_offset" : "0x00000"
}

]
},
{
"is_managed" : true,
"offset_free_hash" : "0xbaa0c9715",
"offset_rich_hash" : "0xbaa0c9afe",
"crashed" : false,
"native_thread_id" : "0x3142c5000",
"thread_info_addr" : "0x7f96af880200",
"thread_name" : "Burst-CompilerThread-6",
"ctx" : {
"IP" : "0x7ff815c365ce",
"SP" : "0x3142c3bd8",
"BP" : "0x3142c3c70"
},
"managed_frames" : [
{
"is_managed" : "false",
"native_address" : "unregistered"
}
,
{
"is_managed" : "true",
"guid" : "EAA95166-E74C-4AE1-A419-B6AA5BAF90B9",
"token" : "0x00000",
"native_offset" : "0x0",
"filename" : "mscorlib.dll",
"sizeofimage" : "0x470000",
"timestamp" : "0x8a9cbcb0",
"il_offset" : "0x00000"
}
,
{
"is_managed" : "true",
"guid" : "EAA95166-E74C-4AE1-A419-B6AA5BAF90B9",
"token" : "0x60020b3",
"native_offset" : "0x0",
"filename" : "mscorlib.dll",
"sizeofimage" : "0x470000",
"timestamp" : "0x8a9cbcb0",
"il_offset" : "0x000c7"
}
,
{
"is_managed" : "true",
"guid" : "EAA95166-E74C-4AE1-A419-B6AA5BAF90B9",
"token" : "0x60020a5",
"native_offset" : "0x0",
"filename" : "mscorlib.dll",
"sizeofimage" : "0x470000",
"timestamp" : "0x8a9cbcb0",
"il_offset" : "0x000a1"
}
,
{
"is_managed" : "true",
"guid" : "EAA95166-E74C-4AE1-A419-B6AA5BAF90B9",
"token" : "0x60020a9",
"native_offset" : "0x0",
"filename" : "mscorlib.dll",
"sizeofimage" : "0x470000",
"timestamp" : "0x8a9cbcb0",
"il_offset" : "0x00000"
}
,
{
"is_managed" : "true",
"guid" : "9BE5D760-D820-4C7D-BC66-320FDD824250",
"token" : "0x6003ffb",
"native_offset" : "0x0",
"filename" : "System.dll",
"sizeofimage" : "0x29a000",
"timestamp" : "0x9dd65995",
"il_offset" : "0x0006e"
}
,
{
"is_managed" : "true",
"guid" : "9BE5D760-D820-4C7D-BC66-320FDD824250",
"token" : "0x6003ffa",
"native_offset" : "0x0",
"filename" : "System.dll",
"sizeofimage" : "0x29a000",
"timestamp" : "0x9dd65995",
"il_offset" : "0x0003c"
}
,
{
"is_managed" : "true",
"guid" : "9BE5D760-D820-4C7D-BC66-320FDD824250",
"token" : "0x6003ff5",
"native_offset" : "0x0",
"filename" : "System.dll",
"sizeofimage" : "0x29a000",
"timestamp" : "0x9dd65995",
"il_offset" : "0x00000"
}
,
{
"is_managed" : "true",
"guid" : "532A8A16-9E6A-4953-B5D9-A4C213B71772",
"token" : "0x6000b49",
"native_offset" : "0x0",
"filename" : "Burst.Compiler.IL.dll",
"sizeofimage" : "0x192000",
"timestamp" : "0x9e316baa",
"il_offset" : "0x00024"
}
,
{
"is_managed" : "true",
"guid" : "532A8A16-9E6A-4953-B5D9-A4C213B71772",
"token" : "0x6000ba5",
"native_offset" : "0x0",
"filename" : "Burst.Compiler.IL.dll",
"sizeofimage" : "0x192000",
"timestamp" : "0x9e316baa",
"il_offset" : "0x00096"
}
,
{
"is_managed" : "true",
"guid" : "EAA95166-E74C-4AE1-A419-B6AA5BAF90B9",
"token" : "0x6001f7d",
"native_offset" : "0x0",
"filename" : "mscorlib.dll",
"sizeofimage" : "0x470000",
"timestamp" : "0x8a9cbcb0",
"il_offset" : "0x00014"
}
,
{
"is_managed" : "true",
"guid" : "EAA95166-E74C-4AE1-A419-B6AA5BAF90B9",
"token" : "0x6001f25",
"native_offset" : "0x0",
"filename" : "mscorlib.dll",
"sizeofimage" : "0x470000",
"timestamp" : "0x8a9cbcb0",
"il_offset" : "0x00071"
}
,
{
"is_managed" : "true",
"guid" : "EAA95166-E74C-4AE1-A419-B6AA5BAF90B9",
"token" : "0x6001f23",
"native_offset" : "0x0",
"filename" : "mscorlib.dll",
"sizeofimage" : "0x470000",
"timestamp" : "0x8a9cbcb0",
"il_offset" : "0x00000"
}
,
{
"is_managed" : "true",
"guid" : "EAA95166-E74C-4AE1-A419-B6AA5BAF90B9",
"token" : "0x6001f22",
"native_offset" : "0x0",
"filename" : "mscorlib.dll",
"sizeofimage" : "0x470000",
"timestamp" : "0x8a9cbcb0",
"il_offset" : "0x0002b"
}
,
{
"is_managed" : "true",
"guid" : "EAA95166-E74C-4AE1-A419-B6AA5BAF90B9",
"token" : "0x6001f7f",
"native_offset" : "0x0",
"filename" : "mscorlib.dll",
"sizeofimage" : "0x470000",
"timestamp" : "0x8a9cbcb0",
"il_offset" : "0x00008"
}
,
{
"is_managed" : "true",
"guid" : "EAA95166-E74C-4AE1-A419-B6AA5BAF90B9",
"token" : "0x00000",
"native_offset" : "0x0",
"filename" : "mscorlib.dll",
"sizeofimage" : "0x470000",
"timestamp" : "0x8a9cbcb0",
"il_offset" : "0x00065"
}

],
"unmanaged_frames" : [
{
"is_managed" : "false",
"native_address" : "0x177367f96",
"native_offset" : "0x00000"
}
,
{
"is_managed" : "false",
"native_address" : "0x1774c129c",
"native_offset" : "0x00000"
}
,
{
"is_managed" : "false",
"native_address" : "0x1774c15d6",
"native_offset" : "0x00000"
}
,
{
"is_managed" : "false",
"native_address" : "0x1774c138d",
"native_offset" : "0x00000"
}
,
{
"is_managed" : "false",
"native_address" : "0x1773c5925",
"native_offset" : "0x00000"
}
,
{
"is_managed" : "false",
"native_address" : "0x7ff815ca137d",
"native_offset" : "0x00000"
}
,
{
"is_managed" : "false",
"native_address" : "0x7ff815a92b44",
"native_offset" : "0x00000"
}
,
{
"is_managed" : "false",
"native_address" : "0x17750ff48",
"native_offset" : "0x00000"
}
,
{
"is_managed" : "false",
"native_address" : "0x1774ccc3c",
"native_offset" : "0x00000"
}
,
{
"is_managed" : "false",
"native_address" : "0x1774cc8e2",
"native_offset" : "0x00000"
}
,
{
"is_managed" : "false",
"native_address" : "0x1774bca56",
"native_offset" : "0x00000"
}
,
{
"is_managed" : "false",
"native_address" : "0x177467b62",
"native_offset" : "0x00000"
}
,
{
"is_managed" : "true",
"guid" : "EAA95166-E74C-4AE1-A419-B6AA5BAF90B9",
"token" : "0x00000",
"native_offset" : "0x0",
"filename" : "mscorlib.dll",
"sizeofimage" : "0x470000",
"timestamp" : "0x8a9cbcb0",
"il_offset" : "0x00000"
}
,
{
"is_managed" : "true",
"guid" : "EAA95166-E74C-4AE1-A419-B6AA5BAF90B9",
"token" : "0x60020a5",
"native_offset" : "0x0",
"filename" : "mscorlib.dll",
"sizeofimage" : "0x470000",
"timestamp" : "0x8a9cbcb0",
"il_offset" : "0x00000"
}

]
},
{
"is_managed" : false,
"offset_free_hash" : "0x0",
"offset_rich_hash" : "0x0",
"crashed" : false,
"native_thread_id" : "0x312092000",
"thread_info_addr" : "0x7f96ab71aa00",
"thread_name" : "Thread Pool Worker",
"ctx" : {
"IP" : "0x7ff815c339c2",
"SP" : "0x312091df8",
"BP" : "0x312091e60"
},
"unmanaged_frames" : [
{
"is_managed" : "false",
"native_address" : "0x177367f96",
"native_offset" : "0x00000"
}
,
{
"is_managed" : "false",
"native_address" : "0x1774c129c",
"native_offset" : "0x00000"
}
,
{
"is_managed" : "false",
"native_address" : "0x1774c15d6",
"native_offset" : "0x00000"
}
,
{
"is_managed" : "false",
"native_address" : "0x1774c138d",
"native_offset" : "0x00000"
}
,
{
"is_managed" : "false",
"native_address" : "0x1773c5925",
"native_offset" : "0x00000"
}
,
{
"is_managed" : "false",
"native_address" : "0x7ff815ca137d",
"native_offset" : "0x00000"
}
,
{
"is_managed" : "false",
"native_address" : "0x3120914c0",
"native_offset" : "0x00000"
}
,
{
"is_managed" : "false",
"native_address" : "0x1774c1fe4",
"native_offset" : "0x00000"
}
,
{
"is_managed" : "false",
"native_address" : "0x1774c1e89",
"native_offset" : "0x00000"
}
,
{
"is_managed" : "false",
"native_address" : "0x17753f3a5",
"native_offset" : "0x00000"
}
,
{
"is_managed" : "false",
"native_address" : "0x17753f33d",
"native_offset" : "0x00000"
}
,
{
"is_managed" : "false",
"native_address" : "0x7ff815c73202",
"native_offset" : "0x00000"
}
,
{
"is_managed" : "false",
"native_address" : "0x7ff815c6ebab",
"native_offset" : "0x00000"
}

]
},
{
"is_managed" : false,
"offset_free_hash" : "0x0",
"offset_rich_hash" : "0x0",
"crashed" : false,
"native_thread_id" : "0x31269b000",
"thread_info_addr" : "0x7f96da1a1600",
"thread_name" : "Thread Pool Worker",
"ctx" : {
"IP" : "0x7ff815c339c2",
"SP" : "0x31269adf8",
"BP" : "0x31269ae60"
},
"unmanaged_frames" : [
{
"is_managed" : "false",
"native_address" : "0x177367f96",
"native_offset" : "0x00000"
}
,
{
"is_managed" : "false",
"native_address" : "0x1774c129c",
"native_offset" : "0x00000"
}
,
{
"is_managed" : "false",
"native_address" : "0x1774c15d6",
"native_offset" : "0x00000"
}
,
{
"is_managed" : "false",
"native_address" : "0x1774c138d",
"native_offset" : "0x00000"
}
,
{
"is_managed" : "false",
"native_address" : "0x1773c5925",
"native_offset" : "0x00000"
}
,
{
"is_managed" : "false",
"native_address" : "0x7ff815ca137d",
"native_offset" : "0x00000"
}
,
{
"is_managed" : "false",
"native_address" : "unregistered"
}
,
{
"is_managed" : "false",
"native_address" : "0x1774c1fe4",
"native_offset" : "0x00000"
}
,
{
"is_managed" : "false",
"native_address" : "0x1774c1e89",
"native_offset" : "0x00000"
}
,
{
"is_managed" : "false",
"native_address" : "0x17753f3a5",
"native_offset" : "0x00000"
}
,
{
"is_managed" : "false",
"native_address" : "0x17753f33d",
"native_offset" : "0x00000"
}
,
{
"is_managed" : "false",
"native_address" : "0x7ff815c73202",
"native_offset" : "0x00000"
}
,
{
"is_managed" : "false",
"native_address" : "0x7ff815c6ebab",
"native_offset" : "0x00000"
}

]
},
{
"is_managed" : true,
"offset_free_hash" : "0xbaa0c9715",
"offset_rich_hash" : "0xbaa0c9afe",
"crashed" : false,
"native_thread_id" : "0x3138b6000",
"thread_info_addr" : "0x7f96ae3d5600",
"thread_name" : "Burst-CompilerThread-1",
"ctx" : {
"IP" : "0x7ff815c365ce",
"SP" : "0x3138b4bd8",
"BP" : "0x3138b4c70"
},
"managed_frames" : [
{
"is_managed" : "false",
"native_address" : "unregistered"
}
,
{
"is_managed" : "true",
"guid" : "EAA95166-E74C-4AE1-A419-B6AA5BAF90B9",
"token" : "0x00000",
"native_offset" : "0x0",
"filename" : "mscorlib.dll",
"sizeofimage" : "0x470000",
"timestamp" : "0x8a9cbcb0",
"il_offset" : "0x00000"
}
,
{
"is_managed" : "true",
"guid" : "EAA95166-E74C-4AE1-A419-B6AA5BAF90B9",
"token" : "0x60020b3",
"native_offset" : "0x0",
"filename" : "mscorlib.dll",
"sizeofimage" : "0x470000",
"timestamp" : "0x8a9cbcb0",
"il_offset" : "0x000c7"
}
,
{
"is_managed" : "true",
"guid" : "EAA95166-E74C-4AE1-A419-B6AA5BAF90B9",
"token" : "0x60020a5",
"native_offset" : "0x0",
"filename" : "mscorlib.dll",
"sizeofimage" : "0x470000",
"timestamp" : "0x8a9cbcb0",
"il_offset" : "0x000a1"
}
,
{
"is_managed" : "true",
"guid" : "EAA95166-E74C-4AE1-A419-B6AA5BAF90B9",
"token" : "0x60020a9",
"native_offset" : "0x0",
"filename" : "mscorlib.dll",
"sizeofimage" : "0x470000",
"timestamp" : "0x8a9cbcb0",
"il_offset" : "0x00000"
}
,
{
"is_managed" : "true",
"guid" : "9BE5D760-D820-4C7D-BC66-320FDD824250",
"token" : "0x6003ffb",
"native_offset" : "0x0",
"filename" : "System.dll",
"sizeofimage" : "0x29a000",
"timestamp" : "0x9dd65995",
"il_offset" : "0x0006e"
}
,
{
"is_managed" : "true",
"guid" : "9BE5D760-D820-4C7D-BC66-320FDD824250",
"token" : "0x6003ffa",
"native_offset" : "0x0",
"filename" : "System.dll",
"sizeofimage" : "0x29a000",
"timestamp" : "0x9dd65995",
"il_offset" : "0x0003c"
}
,
{
"is_managed" : "true",
"guid" : "9BE5D760-D820-4C7D-BC66-320FDD824250",
"token" : "0x6003ff5",
"native_offset" : "0x0",
"filename" : "System.dll",
"sizeofimage" : "0x29a000",
"timestamp" : "0x9dd65995",
"il_offset" : "0x00000"
}
,
{
"is_managed" : "true",
"guid" : "532A8A16-9E6A-4953-B5D9-A4C213B71772",
"token" : "0x6000b49",
"native_offset" : "0x0",
"filename" : "Burst.Compiler.IL.dll",
"sizeofimage" : "0x192000",
"timestamp" : "0x9e316baa",
"il_offset" : "0x00024"
}
,
{
"is_managed" : "true",
"guid" : "532A8A16-9E6A-4953-B5D9-A4C213B71772",
"token" : "0x6000ba5",
"native_offset" : "0x0",
"filename" : "Burst.Compiler.IL.dll",
"sizeofimage" : "0x192000",
"timestamp" : "0x9e316baa",
"il_offset" : "0x00096"
}
,
{
"is_managed" : "true",
"guid" : "EAA95166-E74C-4AE1-A419-B6AA5BAF90B9",
"token" : "0x6001f7d",
"native_offset" : "0x0",
"filename" : "mscorlib.dll",
"sizeofimage" : "0x470000",
"timestamp" : "0x8a9cbcb0",
"il_offset" : "0x00014"
}
,
{
"is_managed" : "true",
"guid" : "EAA95166-E74C-4AE1-A419-B6AA5BAF90B9",
"token" : "0x6001f25",
"native_offset" : "0x0",
"filename" : "mscorlib.dll",
"sizeofimage" : "0x470000",
"timestamp" : "0x8a9cbcb0",
"il_offset" : "0x00071"
}
,
{
"is_managed" : "true",
"guid" : "EAA95166-E74C-4AE1-A419-B6AA5BAF90B9",
"token" : "0x6001f23",
"native_offset" : "0x0",
"filename" : "mscorlib.dll",
"sizeofimage" : "0x470000",
"timestamp" : "0x8a9cbcb0",
"il_offset" : "0x00000"
}
,
{
"is_managed" : "true",
"guid" : "EAA95166-E74C-4AE1-A419-B6AA5BAF90B9",
"token" : "0x6001f22",
"native_offset" : "0x0",
"filename" : "mscorlib.dll",
"sizeofimage" : "0x470000",
"timestamp" : "0x8a9cbcb0",
"il_offset" : "0x0002b"
}
,
{
"is_managed" : "true",
"guid" : "EAA95166-E74C-4AE1-A419-B6AA5BAF90B9",
"token" : "0x6001f7f",
"native_offset" : "0x0",
"filename" : "mscorlib.dll",
"sizeofimage" : "0x470000",
"timestamp" : "0x8a9cbcb0",
"il_offset" : "0x00008"
}
,
{
"is_managed" : "true",
"guid" : "EAA95166-E74C-4AE1-A419-B6AA5BAF90B9",
"token" : "0x00000",
"native_offset" : "0x0",
"filename" : "mscorlib.dll",
"sizeofimage" : "0x470000",
"timestamp" : "0x8a9cbcb0",
"il_offset" : "0x00065"
}

],
"unmanaged_frames" : [
{
"is_managed" : "false",
"native_address" : "0x177367f96",
"native_offset" : "0x00000"
}
,
{
"is_managed" : "false",
"native_address" : "0x1774c129c",
"native_offset" : "0x00000"
}
,
{
"is_managed" : "false",
"native_address" : "0x1774c15d6",
"native_offset" : "0x00000"
}
,
{
"is_managed" : "false",
"native_address" : "0x1774c138d",
"native_offset" : "0x00000"
}
,
{
"is_managed" : "false",
"native_address" : "0x1773c5925",
"native_offset" : "0x00000"
}
,
{
"is_managed" : "false",
"native_address" : "0x7ff815ca137d",
"native_offset" : "0x00000"
}
,
{
"is_managed" : "false",
"native_address" : "0x1c7f1b85c",
"native_offset" : "0x00000"
}
,
{
"is_managed" : "false",
"native_address" : "0x17750ff48",
"native_offset" : "0x00000"
}
,
{
"is_managed" : "false",
"native_address" : "0x1774ccc3c",
"native_offset" : "0x00000"
}
,
{
"is_managed" : "false",
"native_address" : "0x1774cc8e2",
"native_offset" : "0x00000"
}
,
{
"is_managed" : "false",
"native_address" : "0x1774bca56",
"native_offset" : "0x00000"
}
,
{
"is_managed" : "false",
"native_address" : "0x177467b62",
"native_offset" : "0x00000"
}
,
{
"is_managed" : "true",
"guid" : "EAA95166-E74C-4AE1-A419-B6AA5BAF90B9",
"token" : "0x00000",
"native_offset" : "0x0",
"filename" : "mscorlib.dll",
"sizeofimage" : "0x470000",
"timestamp" : "0x8a9cbcb0",
"il_offset" : "0x00000"
}
,
{
"is_managed" : "true",
"guid" : "EAA95166-E74C-4AE1-A419-B6AA5BAF90B9",
"token" : "0x60020a5",
"native_offset" : "0x0",
"filename" : "mscorlib.dll",
"sizeofimage" : "0x470000",
"timestamp" : "0x8a9cbcb0",
"il_offset" : "0x00000"
}

]
},
{
"is_managed" : false,
"offset_free_hash" : "0x0",
"offset_rich_hash" : "0x0",
"crashed" : false,
"native_thread_id" : "0x311983000",
"thread_info_addr" : "0x7f96d9967e00",
"thread_name" : "Debugger agent",
"ctx" : {
"IP" : "0x7ff815c3a832",
"SP" : "0x311982ae8",
"BP" : "0x311982b20"
},
"unmanaged_frames" : [
{
"is_managed" : "false",
"native_address" : "0x177367f96",
"native_offset" : "0x00000"
}
,
{
"is_managed" : "false",
"native_address" : "0x1774c129c",
"native_offset" : "0x00000"
}
,
{
"is_managed" : "false",
"native_address" : "0x1774c15d6",
"native_offset" : "0x00000"
}
,
{
"is_managed" : "false",
"native_address" : "0x1774c138d",
"native_offset" : "0x00000"
}
,
{
"is_managed" : "false",
"native_address" : "0x1773c5925",
"native_offset" : "0x00000"
}
,
{
"is_managed" : "false",
"native_address" : "0x7ff815ca137d",
"native_offset" : "0x00000"
}
,
{
"is_managed" : "false",
"native_address" : "unregistered"
}
,
{
"is_managed" : "false",
"native_address" : "0x1773ef734",
"native_offset" : "0x00000"
}
,
{
"is_managed" : "false",
"native_address" : "0x1774c1fe4",
"native_offset" : "0x00000"
}
,
{
"is_managed" : "false",
"native_address" : "0x1774c1e89",
"native_offset" : "0x00000"
}
,
{
"is_managed" : "false",
"native_address" : "0x17753f3a5",
"native_offset" : "0x00000"
}
,
{
"is_managed" : "false",
"native_address" : "0x17753f33d",
"native_offset" : "0x00000"
}
,
{
"is_managed" : "false",
"native_address" : "0x7ff815c73202",
"native_offset" : "0x00000"
}
,
{
"is_managed" : "false",
"native_address" : "0x7ff815c6ebab",
"native_offset" : "0x00000"
}

]
},
{
"is_managed" : true,
"offset_free_hash" : "0xbaa0c9715",
"offset_rich_hash" : "0xbaa0c9afe",
"crashed" : false,
"native_thread_id" : "0x313ebf000",
"thread_info_addr" : "0x7f96adfc5a00",
"thread_name" : "Burst-CompilerThread-4",
"ctx" : {
"IP" : "0x7ff815c365ce",
"SP" : "0x313ebdbd8",
"BP" : "0x313ebdc70"
},
"managed_frames" : [
{
"is_managed" : "false",
"native_address" : "unregistered"
}
,
{
"is_managed" : "true",
"guid" : "EAA95166-E74C-4AE1-A419-B6AA5BAF90B9",
"token" : "0x00000",
"native_offset" : "0x0",
"filename" : "mscorlib.dll",
"sizeofimage" : "0x470000",
"timestamp" : "0x8a9cbcb0",
"il_offset" : "0x00000"
}
,
{
"is_managed" : "true",
"guid" : "EAA95166-E74C-4AE1-A419-B6AA5BAF90B9",
"token" : "0x60020b3",
"native_offset" : "0x0",
"filename" : "mscorlib.dll",
"sizeofimage" : "0x470000",
"timestamp" : "0x8a9cbcb0",
"il_offset" : "0x000c7"
}
,
{
"is_managed" : "true",
"guid" : "EAA95166-E74C-4AE1-A419-B6AA5BAF90B9",
"token" : "0x60020a5",
"native_offset" : "0x0",
"filename" : "mscorlib.dll",
"sizeofimage" : "0x470000",
"timestamp" : "0x8a9cbcb0",
"il_offset" : "0x000a1"
}
,
{
"is_managed" : "true",
"guid" : "EAA95166-E74C-4AE1-A419-B6AA5BAF90B9",
"token" : "0x60020a9",
"native_offset" : "0x0",
"filename" : "mscorlib.dll",
"sizeofimage" : "0x470000",
"timestamp" : "0x8a9cbcb0",
"il_offset" : "0x00000"
}
,
{
"is_managed" : "true",
"guid" : "9BE5D760-D820-4C7D-BC66-320FDD824250",
"token" : "0x6003ffb",
"native_offset" : "0x0",
"filename" : "System.dll",
"sizeofimage" : "0x29a000",
"timestamp" : "0x9dd65995",
"il_offset" : "0x0006e"
}
,
{
"is_managed" : "true",
"guid" : "9BE5D760-D820-4C7D-BC66-320FDD824250",
"token" : "0x6003ffa",
"native_offset" : "0x0",
"filename" : "System.dll",
"sizeofimage" : "0x29a000",
"timestamp" : "0x9dd65995",
"il_offset" : "0x0003c"
}
,
{
"is_managed" : "true",
"guid" : "9BE5D760-D820-4C7D-BC66-320FDD824250",
"token" : "0x6003ff5",
"native_offset" : "0x0",
"filename" : "System.dll",
"sizeofimage" : "0x29a000",
"timestamp" : "0x9dd65995",
"il_offset" : "0x00000"
}
,
{
"is_managed" : "true",
"guid" : "532A8A16-9E6A-4953-B5D9-A4C213B71772",
"token" : "0x6000b49",
"native_offset" : "0x0",
"filename" : "Burst.Compiler.IL.dll",
"sizeofimage" : "0x192000",
"timestamp" : "0x9e316baa",
"il_offset" : "0x00024"
}
,
{
"is_managed" : "true",
"guid" : "532A8A16-9E6A-4953-B5D9-A4C213B71772",
"token" : "0x6000ba5",
"native_offset" : "0x0",
"filename" : "Burst.Compiler.IL.dll",
"sizeofimage" : "0x192000",
"timestamp" : "0x9e316baa",
"il_offset" : "0x00096"
}
,
{
"is_managed" : "true",
"guid" : "EAA95166-E74C-4AE1-A419-B6AA5BAF90B9",
"token" : "0x6001f7d",
"native_offset" : "0x0",
"filename" : "mscorlib.dll",
"sizeofimage" : "0x470000",
"timestamp" : "0x8a9cbcb0",
"il_offset" : "0x00014"
}
,
{
"is_managed" : "true",
"guid" : "EAA95166-E74C-4AE1-A419-B6AA5BAF90B9",
"token" : "0x6001f25",
"native_offset" : "0x0",
"filename" : "mscorlib.dll",
"sizeofimage" : "0x470000",
"timestamp" : "0x8a9cbcb0",
"il_offset" : "0x00071"
}
,
{
"is_managed" : "true",
"guid" : "EAA95166-E74C-4AE1-A419-B6AA5BAF90B9",
"token" : "0x6001f23",
"native_offset" : "0x0",
"filename" : "mscorlib.dll",
"sizeofimage" : "0x470000",
"timestamp" : "0x8a9cbcb0",
"il_offset" : "0x00000"
}
,
{
"is_managed" : "true",
"guid" : "EAA95166-E74C-4AE1-A419-B6AA5BAF90B9",
"token" : "0x6001f22",
"native_offset" : "0x0",
"filename" : "mscorlib.dll",
"sizeofimage" : "0x470000",
"timestamp" : "0x8a9cbcb0",
"il_offset" : "0x0002b"
}
,
{
"is_managed" : "true",
"guid" : "EAA95166-E74C-4AE1-A419-B6AA5BAF90B9",
"token" : "0x6001f7f",
"native_offset" : "0x0",
"filename" : "mscorlib.dll",
"sizeofimage" : "0x470000",
"timestamp" : "0x8a9cbcb0",
"il_offset" : "0x00008"
}
,
{
"is_managed" : "true",
"guid" : "EAA95166-E74C-4AE1-A419-B6AA5BAF90B9",
"token" : "0x00000",
"native_offset" : "0x0",
"filename" : "mscorlib.dll",
"sizeofimage" : "0x470000",
"timestamp" : "0x8a9cbcb0",
"il_offset" : "0x00065"
}

],
"unmanaged_frames" : [
{
"is_managed" : "false",
"native_address" : "0x177367f96",
"native_offset" : "0x00000"
}
,
{
"is_managed" : "false",
"native_address" : "0x1774c129c",
"native_offset" : "0x00000"
}
,
{
"is_managed" : "false",
"native_address" : "0x1774c15d6",
"native_offset" : "0x00000"
}
,
{
"is_managed" : "false",
"native_address" : "0x1774c138d",
"native_offset" : "0x00000"
}
,
{
"is_managed" : "false",
"native_address" : "0x1773c5925",
"native_offset" : "0x00000"
}
,
{
"is_managed" : "false",
"native_address" : "0x7ff815ca137d",
"native_offset" : "0x00000"
}
,
{
"is_managed" : "false",
"native_address" : "0x1a5ce511c",
"native_offset" : "0x00000"
}
,
{
"is_managed" : "false",
"native_address" : "0x17750ff48",
"native_offset" : "0x00000"
}
,
{
"is_managed" : "false",
"native_address" : "0x1774ccc3c",
"native_offset" : "0x00000"
}
,
{
"is_managed" : "false",
"native_address" : "0x1774cc8e2",
"native_offset" : "0x00000"
}
,
{
"is_managed" : "false",
"native_address" : "0x1774bca56",
"native_offset" : "0x00000"
}
,
{
"is_managed" : "false",
"native_address" : "0x177467b62",
"native_offset" : "0x00000"
}
,
{
"is_managed" : "true",
"guid" : "EAA95166-E74C-4AE1-A419-B6AA5BAF90B9",
"token" : "0x00000",
"native_offset" : "0x0",
"filename" : "mscorlib.dll",
"sizeofimage" : "0x470000",
"timestamp" : "0x8a9cbcb0",
"il_offset" : "0x00000"
}
,
{
"is_managed" : "true",
"guid" : "EAA95166-E74C-4AE1-A419-B6AA5BAF90B9",
"token" : "0x60020a5",
"native_offset" : "0x0",
"filename" : "mscorlib.dll",
"sizeofimage" : "0x470000",
"timestamp" : "0x8a9cbcb0",
"il_offset" : "0x00000"
}

]
},
{
"is_managed" : false,
"offset_free_hash" : "0x0",
"offset_rich_hash" : "0x0",
"crashed" : false,
"native_thread_id" : "0x3102ce000",
"thread_info_addr" : "0x7f96b8c26a00",
"thread_name" : "tid_12703",
"ctx" : {
"IP" : "0x7ff815c339aa",
"SP" : "0x3102cdd18",
"BP" : "0x3102cdd30"
},
"unmanaged_frames" : [
{
"is_managed" : "false",
"native_address" : "0x177367f96",
"native_offset" : "0x00000"
}
,
{
"is_managed" : "false",
"native_address" : "0x1774c129c",
"native_offset" : "0x00000"
}
,
{
"is_managed" : "false",
"native_address" : "0x1774c15d6",
"native_offset" : "0x00000"
}
,
{
"is_managed" : "false",
"native_address" : "0x1774c138d",
"native_offset" : "0x00000"
}
,
{
"is_managed" : "false",
"native_address" : "0x1773c5925",
"native_offset" : "0x00000"
}
,
{
"is_managed" : "false",
"native_address" : "0x7ff815ca137d",
"native_offset" : "0x00000"
}
,
{
"is_managed" : "false",
"native_address" : "0x1000000000",
"native_offset" : "0x00000"
}
,
{
"is_managed" : "false",
"native_address" : "0x7ff815acbf5f",
"native_offset" : "0x00000"
}
,
{
"is_managed" : "false",
"native_address" : "0x1052811e8",
"native_offset" : "0x00000"
}
,
{
"is_managed" : "false",
"native_address" : "0x102c2703a",
"native_offset" : "0x00000"
}
,
{
"is_managed" : "false",
"native_address" : "0x102c285f5",
"native_offset" : "0x00000"
}
,
{
"is_managed" : "false",
"native_address" : "0x102eb8d3b",
"native_offset" : "0x00000"
}
,
{
"is_managed" : "false",
"native_address" : "0x7ff815c73202",
"native_offset" : "0x00000"
}
,
{
"is_managed" : "false",
"native_address" : "0x7ff815c6ebab",
"native_offset" : "0x00000"
}

]
},
{
"is_managed" : true,
"offset_free_hash" : "0xbaa0c9715",
"offset_rich_hash" : "0xbaa0c9afe",
"crashed" : false,
"native_thread_id" : "0x3144c8000",
"thread_info_addr" : "0x7f96c8951600",
"thread_name" : "Burst-CompilerThread-7",
"ctx" : {
"IP" : "0x7ff815c365ce",
"SP" : "0x3144c6bd8",
"BP" : "0x3144c6c70"
},
"managed_frames" : [
{
"is_managed" : "false",
"native_address" : "unregistered"
}
,
{
"is_managed" : "true",
"guid" : "EAA95166-E74C-4AE1-A419-B6AA5BAF90B9",
"token" : "0x00000",
"native_offset" : "0x0",
"filename" : "mscorlib.dll",
"sizeofimage" : "0x470000",
"timestamp" : "0x8a9cbcb0",
"il_offset" : "0x00000"
}
,
{
"is_managed" : "true",
"guid" : "EAA95166-E74C-4AE1-A419-B6AA5BAF90B9",
"token" : "0x60020b3",
"native_offset" : "0x0",
"filename" : "mscorlib.dll",
"sizeofimage" : "0x470000",
"timestamp" : "0x8a9cbcb0",
"il_offset" : "0x000c7"
}
,
{
"is_managed" : "true",
"guid" : "EAA95166-E74C-4AE1-A419-B6AA5BAF90B9",
"token" : "0x60020a5",
"native_offset" : "0x0",
"filename" : "mscorlib.dll",
"sizeofimage" : "0x470000",
"timestamp" : "0x8a9cbcb0",
"il_offset" : "0x000a1"
}
,
{
"is_managed" : "true",
"guid" : "EAA95166-E74C-4AE1-A419-B6AA5BAF90B9",
"token" : "0x60020a9",
"native_offset" : "0x0",
"filename" : "mscorlib.dll",
"sizeofimage" : "0x470000",
"timestamp" : "0x8a9cbcb0",
"il_offset" : "0x00000"
}
,
{
"is_managed" : "true",
"guid" : "9BE5D760-D820-4C7D-BC66-320FDD824250",
"token" : "0x6003ffb",
"native_offset" : "0x0",
"filename" : "System.dll",
"sizeofimage" : "0x29a000",
"timestamp" : "0x9dd65995",
"il_offset" : "0x0006e"
}
,
{
"is_managed" : "true",
"guid" : "9BE5D760-D820-4C7D-BC66-320FDD824250",
"token" : "0x6003ffa",
"native_offset" : "0x0",
"filename" : "System.dll",
"sizeofimage" : "0x29a000",
"timestamp" : "0x9dd65995",
"il_offset" : "0x0003c"
}
,
{
"is_managed" : "true",
"guid" : "9BE5D760-D820-4C7D-BC66-320FDD824250",
"token" : "0x6003ff5",
"native_offset" : "0x0",
"filename" : "System.dll",
"sizeofimage" : "0x29a000",
"timestamp" : "0x9dd65995",
"il_offset" : "0x00000"
}
,
{
"is_managed" : "true",
"guid" : "532A8A16-9E6A-4953-B5D9-A4C213B71772",
"token" : "0x6000b49",
"native_offset" : "0x0",
"filename" : "Burst.Compiler.IL.dll",
"sizeofimage" : "0x192000",
"timestamp" : "0x9e316baa",
"il_offset" : "0x00024"
}
,
{
"is_managed" : "true",
"guid" : "532A8A16-9E6A-4953-B5D9-A4C213B71772",
"token" : "0x6000ba5",
"native_offset" : "0x0",
"filename" : "Burst.Compiler.IL.dll",
"sizeofimage" : "0x192000",
"timestamp" : "0x9e316baa",
"il_offset" : "0x00096"
}
,
{
"is_managed" : "true",
"guid" : "EAA95166-E74C-4AE1-A419-B6AA5BAF90B9",
"token" : "0x6001f7d",
"native_offset" : "0x0",
"filename" : "mscorlib.dll",
"sizeofimage" : "0x470000",
"timestamp" : "0x8a9cbcb0",
"il_offset" : "0x00014"
}
,
{
"is_managed" : "true",
"guid" : "EAA95166-E74C-4AE1-A419-B6AA5BAF90B9",
"token" : "0x6001f25",
"native_offset" : "0x0",
"filename" : "mscorlib.dll",
"sizeofimage" : "0x470000",
"timestamp" : "0x8a9cbcb0",
"il_offset" : "0x00071"
}
,
{
"is_managed" : "true",
"guid" : "EAA95166-E74C-4AE1-A419-B6AA5BAF90B9",
"token" : "0x6001f23",
"native_offset" : "0x0",
"filename" : "mscorlib.dll",
"sizeofimage" : "0x470000",
"timestamp" : "0x8a9cbcb0",
"il_offset" : "0x00000"
}
,
{
"is_managed" : "true",
"guid" : "EAA95166-E74C-4AE1-A419-B6AA5BAF90B9",
"token" : "0x6001f22",
"native_offset" : "0x0",
"filename" : "mscorlib.dll",
"sizeofimage" : "0x470000",
"timestamp" : "0x8a9cbcb0",
"il_offset" : "0x0002b"
}
,
{
"is_managed" : "true",
"guid" : "EAA95166-E74C-4AE1-A419-B6AA5BAF90B9",
"token" : "0x6001f7f",
"native_offset" : "0x0",
"filename" : "mscorlib.dll",
"sizeofimage" : "0x470000",
"timestamp" : "0x8a9cbcb0",
"il_offset" : "0x00008"
}
,
{
"is_managed" : "true",
"guid" : "EAA95166-E74C-4AE1-A419-B6AA5BAF90B9",
"token" : "0x00000",
"native_offset" : "0x0",
"filename" : "mscorlib.dll",
"sizeofimage" : "0x470000",
"timestamp" : "0x8a9cbcb0",
"il_offset" : "0x00065"
}

],
"unmanaged_frames" : [
{
"is_managed" : "false",
"native_address" : "0x177367f96",
"native_offset" : "0x00000"
}
,
{
"is_managed" : "false",
"native_address" : "0x1774c129c",
"native_offset" : "0x00000"
}
,
{
"is_managed" : "false",
"native_address" : "0x1774c15d6",
"native_offset" : "0x00000"
}
,
{
"is_managed" : "false",
"native_address" : "0x1774c138d",
"native_offset" : "0x00000"
}
,
{
"is_managed" : "false",
"native_address" : "0x1773c5925",
"native_offset" : "0x00000"
}
,
{
"is_managed" : "false",
"native_address" : "0x7ff815ca137d",
"native_offset" : "0x00000"
}
,
{
"is_managed" : "false",
"native_address" : "unregistered"
}
,
{
"is_managed" : "false",
"native_address" : "0x17750ff48",
"native_offset" : "0x00000"
}
,
{
"is_managed" : "false",
"native_address" : "0x1774ccc3c",
"native_offset" : "0x00000"
}
,
{
"is_managed" : "false",
"native_address" : "0x1774cc8e2",
"native_offset" : "0x00000"
}
,
{
"is_managed" : "false",
"native_address" : "0x1774bca56",
"native_offset" : "0x00000"
}
,
{
"is_managed" : "false",
"native_address" : "0x177467b62",
"native_offset" : "0x00000"
}
,
{
"is_managed" : "true",
"guid" : "EAA95166-E74C-4AE1-A419-B6AA5BAF90B9",
"token" : "0x00000",
"native_offset" : "0x0",
"filename" : "mscorlib.dll",
"sizeofimage" : "0x470000",
"timestamp" : "0x8a9cbcb0",
"il_offset" : "0x00000"
}
,
{
"is_managed" : "true",
"guid" : "EAA95166-E74C-4AE1-A419-B6AA5BAF90B9",
"token" : "0x60020a5",
"native_offset" : "0x0",
"filename" : "mscorlib.dll",
"sizeofimage" : "0x470000",
"timestamp" : "0x8a9cbcb0",
"il_offset" : "0x00000"
}

]
},
{
"is_managed" : false,
"offset_free_hash" : "0x0",
"offset_rich_hash" : "0x0",
"crashed" : false,
"native_thread_id" : "0x312295000",
"thread_info_addr" : "0x7f96acb66800",
"thread_name" : "tid_2bc0f",
"ctx" : {
"IP" : "0x7ff815c365ce",
"SP" : "0x312294cc8",
"BP" : "0x312294d60"
},
"unmanaged_frames" : [
{
"is_managed" : "false",
"native_address" : "0x177367f96",
"native_offset" : "0x00000"
}
,
{
"is_managed" : "false",
"native_address" : "0x1774c129c",
"native_offset" : "0x00000"
}
,
{
"is_managed" : "false",
"native_address" : "0x1774c15d6",
"native_offset" : "0x00000"
}
,
{
"is_managed" : "false",
"native_address" : "0x1774c138d",
"native_offset" : "0x00000"
}
,
{
"is_managed" : "false",
"native_address" : "0x1773c5925",
"native_offset" : "0x00000"
}
,
{
"is_managed" : "false",
"native_address" : "0x7ff815ca137d",
"native_offset" : "0x00000"
}
,
{
"is_managed" : "false",
"native_address" : "unregistered"
}
,
{
"is_managed" : "false",
"native_address" : "0x17750ff2c",
"native_offset" : "0x00000"
}
,
{
"is_managed" : "false",
"native_address" : "0x177519efa",
"native_offset" : "0x00000"
}
,
{
"is_managed" : "false",
"native_address" : "0x17741a7ce",
"native_offset" : "0x00000"
}
,
{
"is_managed" : "false",
"native_address" : "0x1774c1fe4",
"native_offset" : "0x00000"
}
,
{
"is_managed" : "false",
"native_address" : "0x1774c1e89",
"native_offset" : "0x00000"
}
,
{
"is_managed" : "false",
"native_address" : "0x17753f3a5",
"native_offset" : "0x00000"
}
,
{
"is_managed" : "false",
"native_address" : "0x17753f33d",
"native_offset" : "0x00000"
}
,
{
"is_managed" : "false",
"native_address" : "0x7ff815c73202",
"native_offset" : "0x00000"
}
,
{
"is_managed" : "false",
"native_address" : "0x7ff815c6ebab",
"native_offset" : "0x00000"
}

]
},
{
"is_managed" : false,
"offset_free_hash" : "0x0",
"offset_rich_hash" : "0x0",
"crashed" : false,
"native_thread_id" : "0x31289e000",
"thread_info_addr" : "0x7f96d9824c00",
"thread_name" : "Thread Pool I/O Selector",
"ctx" : {
"IP" : "0x7ff815c3c91e",
"SP" : "0x31289db78",
"BP" : "0x31289dd50"
},
"unmanaged_frames" : [
{
"is_managed" : "false",
"native_address" : "0x177367f96",
"native_offset" : "0x00000"
}
,
{
"is_managed" : "false",
"native_address" : "0x1774c129c",
"native_offset" : "0x00000"
}
,
{
"is_managed" : "false",
"native_address" : "0x1774c15d6",
"native_offset" : "0x00000"
}
,
{
"is_managed" : "false",
"native_address" : "0x1774c138d",
"native_offset" : "0x00000"
}
,
{
"is_managed" : "false",
"native_address" : "0x1773c5925",
"native_offset" : "0x00000"
}
,
{
"is_managed" : "false",
"native_address" : "0x7ff815ca137d",
"native_offset" : "0x00000"
}
,
{
"is_managed" : "false",
"native_address" : "unregistered"
}
,
{
"is_managed" : "false",
"native_address" : "0x1774c61c0",
"native_offset" : "0x00000"
}
,
{
"is_managed" : "false",
"native_address" : "0x1774c5c49",
"native_offset" : "0x00000"
}
,
{
"is_managed" : "false",
"native_address" : "0x1774c1fe4",
"native_offset" : "0x00000"
}
,
{
"is_managed" : "false",
"native_address" : "0x1774c1e89",
"native_offset" : "0x00000"
}
,
{
"is_managed" : "false",
"native_address" : "0x17753f3a5",
"native_offset" : "0x00000"
}
,
{
"is_managed" : "false",
"native_address" : "0x17753f33d",
"native_offset" : "0x00000"
}
,
{
"is_managed" : "false",
"native_address" : "0x7ff815c73202",
"native_offset" : "0x00000"
}
,
{
"is_managed" : "false",
"native_address" : "0x7ff815c6ebab",
"native_offset" : "0x00000"
}

]
}
]
}